analisador_texto_pt_br_e_eng/__init__.py
analisador_texto_pt_br_e_eng/analisador_texto_pt_br/__init__.py
analisador_texto_pt_br_e_eng/analisador_texto_pt_br/pt_br.py
analisador_texto_pt_br_e_eng/analyze_text_eng/__init__.py
analisador_texto_pt_br_e_eng/analyze_text_eng/eng.py
Analisador_Texto_pt_br_e_ingles-0.0.1.dist-info/METADATA
Analisador_Texto_pt_br_e_ingles-0.0.1.dist-info/WHEEL
Analisador_Texto_pt_br_e_ingles-0.0.1.dist-info/top_level.txt
Analisador_Texto_pt_br_e_ingles-0.0.1.dist-info/RECORD
