Metadata-Version: 2.1
Name: Analisador-Texto-pt-br-e-ingles
Version: 0.0.1
Summary: Analisador de texto em português e inglês usando spaCy.
Home-page: https://github.com/alexxs2/package-template
Author: Alexsandro
Author-email: alecsbezerra@gmail.com
Requires-Python: >=3.8
Requires-Dist: spacy (>=3.0)
Requires-Dist: setuptools (>=42)
